MANIFEST.in
README
setup.cfg
setup.py
pythonioc/__about__.py
pythonioc/__init__.py
pythonioc/serviceproxy.py
pythonioc/serviceregistry.py
pythonioc.egg-info/PKG-INFO
pythonioc.egg-info/SOURCES.txt
pythonioc.egg-info/dependency_links.txt
pythonioc.egg-info/requires.txt
pythonioc.egg-info/top_level.txt
pythonioc/test/__init__.py
pythonioc/test/test_decorators.py
pythonioc/test/test_depcycle.py
pythonioc/test/test_globalserviceregistry.py
pythonioc/test/test_pythonioc.py
pythonioc/test/test_serviceproxy.py
pythonioc/test/test_serviceregistry.py