Metadata-Version: 1.0
Name: pythonioc
Version: 0.4.1
Summary: Simplistic dependency injection container for python
Home-page: https://bitbucket.org/eh14/python-ioc
Author: Franz Eichhorn
Author-email: frairon@googlemail.com
License: MIT
Platform: UNKNOWN
